opencensus/__init__.py
opencensus/extension/__init__.py
opencensus/extension/azure/functions.py
opencensus/extension/azure/version.py
opencensus_extension_azure_functions-1.0.0.dist-info/LICENSE
opencensus_extension_azure_functions-1.0.0.dist-info/METADATA
opencensus_extension_azure_functions-1.0.0.dist-info/WHEEL
opencensus_extension_azure_functions-1.0.0.dist-info/top_level.txt
opencensus_extension_azure_functions-1.0.0.dist-info/RECORD
