Metadata-Version: 2.1
Name: opencensus-extension-azure-functions
Version: 1.0.0
Summary: OpenCensus extension for Azure Functions
Home-page: https://github.com/census-ecosystem/opencensus-python-extensions-azure
Author: OpenCensus Azure
Author-email: opencensusazure@microsoft.com
License: Apache-2.0
Platform: UNKNOWN
Classifier: Intended Audience :: End Users/Desktop
Classifier: Development Status :: 5 - Production/Stable
Classifier: Intended Audience :: End Users/Desktop
Classifier: License :: OSI Approved :: Apache Software License
Classifier: Programming Language :: Python
Classifier: Programming Language :: Python :: 3.6
Classifier: Programming Language :: Python :: 3.7
Requires-Dist: azure-functions (<2.0.0,>=1.7.0)
Requires-Dist: opencensus-ext-azure (<2.0.0,>=1.0.4)
